[
  {
    "ContainingType": "projeto.Controllers.AlertController",
    "Method": "Post",
    "RelativePath": "Alert",
    "HttpMethod": "POST",
    "IsController": true,
    "Order": 0,
    "Parameters": [
      {
        "Name": "description",
        "Type": "System.String",
        "IsRequired": false
      },
      {
        "Name": "ID_admin",
        "Type": "System.Int32",
        "IsRequired": false
      },
      {
        "Name": "_ID_users",
        "Type": "System.String",
        "IsRequired": false
      }
    ],
    "ReturnTypes": [
      {
        "Type": "System.Void",
        "MediaTypes": [],
        "StatusCode": 200
      }
    ],
    "EndpointName": "PostAlerts"
  },
  {
    "ContainingType": "projeto.Controllers.AlertController",
    "Method": "Get",
    "RelativePath": "Alert",
    "HttpMethod": "GET",
    "IsController": true,
    "Order": 0,
    "Parameters": [],
    "ReturnTypes": [
      {
        "Type": "System.Collections.Generic.IEnumerable\u00601[[projeto.Data.Models.Alert, AMoVeR-Logistica, Version=1.0.0.0, Culture=neutral, PublicKeyToken=null]]",
        "MediaTypes": [
          "text/plain",
          "application/json",
          "text/json"
        ],
        "StatusCode": 200
      }
    ],
    "EndpointName": "GetAlerts"
  },
  {
    "ContainingType": "projeto.Controllers.ReportController",
    "Method": "Post",
    "RelativePath": "Report",
    "HttpMethod": "POST",
    "IsController": true,
    "Order": 0,
    "Parameters": [
      {
        "Name": "description",
        "Type": "System.String",
        "IsRequired": false
      }
    ],
    "ReturnTypes": [
      {
        "Type": "System.Void",
        "MediaTypes": [],
        "StatusCode": 200
      }
    ],
    "EndpointName": "PostReport"
  },
  {
    "ContainingType": "projeto.Controllers.ReportController",
    "Method": "Get",
    "RelativePath": "Report",
    "HttpMethod": "GET",
    "IsController": true,
    "Order": 0,
    "Parameters": [],
    "ReturnTypes": [
      {
        "Type": "System.Collections.Generic.IEnumerable\u00601[[projeto.Data.Models.PerformanceReport, AMoVeR-Logistica, Version=1.0.0.0, Culture=neutral, PublicKeyToken=null]]",
        "MediaTypes": [
          "text/plain",
          "application/json",
          "text/json"
        ],
        "StatusCode": 200
      }
    ],
    "EndpointName": "GetReports"
  },
  {
    "ContainingType": "projeto.Controllers.ServiceController",
    "Method": "Post",
    "RelativePath": "Service",
    "HttpMethod": "POST",
    "IsController": true,
    "Order": 0,
    "Parameters": [
      {
        "Name": "type",
        "Type": "System.String",
        "IsRequired": false
      },
      {
        "Name": "description",
        "Type": "System.String",
        "IsRequired": false
      },
      {
        "Name": "status",
        "Type": "System.String",
        "IsRequired": false
      },
      {
        "Name": "ID",
        "Type": "System.Int32",
        "IsRequired": false
      }
    ],
    "ReturnTypes": [
      {
        "Type": "System.Void",
        "MediaTypes": [],
        "StatusCode": 200
      }
    ],
    "EndpointName": "PostService"
  },
  {
    "ContainingType": "projeto.Controllers.ServiceController",
    "Method": "Get",
    "RelativePath": "Service",
    "HttpMethod": "GET",
    "IsController": true,
    "Order": 0,
    "Parameters": [],
    "ReturnTypes": [
      {
        "Type": "System.Collections.Generic.IEnumerable\u00601[[projeto.Data.Models.Service, AMoVeR-Logistica, Version=1.0.0.0, Culture=neutral, PublicKeyToken=null]]",
        "MediaTypes": [
          "text/plain",
          "application/json",
          "text/json"
        ],
        "StatusCode": 200
      }
    ],
    "EndpointName": "GetServices"
  },
  {
    "ContainingType": "projeto.Controllers.TaskController",
    "Method": "Post",
    "RelativePath": "Task",
    "HttpMethod": "POST",
    "IsController": true,
    "Order": 0,
    "Parameters": [
      {
        "Name": "type",
        "Type": "System.String",
        "IsRequired": false
      },
      {
        "Name": "deadline",
        "Type": "System.DateTime",
        "IsRequired": false
      },
      {
        "Name": "description",
        "Type": "System.String",
        "IsRequired": false
      },
      {
        "Name": "status",
        "Type": "System.String",
        "IsRequired": false
      },
      {
        "Name": "ID",
        "Type": "System.Int32",
        "IsRequired": false
      },
      {
        "Name": "service",
        "Type": "System.Int32",
        "IsRequired": false
      },
      {
        "Name": "coordinates",
        "Type": "System.String",
        "IsRequired": false
      }
    ],
    "ReturnTypes": [
      {
        "Type": "System.Void",
        "MediaTypes": [],
        "StatusCode": 200
      }
    ],
    "EndpointName": "PostTask"
  },
  {
    "ContainingType": "projeto.Controllers.TaskController",
    "Method": "Get",
    "RelativePath": "Task",
    "HttpMethod": "GET",
    "IsController": true,
    "Order": 0,
    "Parameters": [],
    "ReturnTypes": [
      {
        "Type": "System.Collections.Generic.IEnumerable\u00601[[projeto.Data.Models.Task, AMoVeR-Logistica, Version=1.0.0.0, Culture=neutral, PublicKeyToken=null]]",
        "MediaTypes": [
          "text/plain",
          "application/json",
          "text/json"
        ],
        "StatusCode": 200
      }
    ],
    "EndpointName": "GetTasks"
  },
  {
    "ContainingType": "projeto.Controllers.UserController",
    "Method": "Post",
    "RelativePath": "User",
    "HttpMethod": "POST",
    "IsController": true,
    "Order": 0,
    "Parameters": [
      {
        "Name": "name",
        "Type": "System.String",
        "IsRequired": false
      },
      {
        "Name": "email",
        "Type": "System.String",
        "IsRequired": false
      },
      {
        "Name": "password",
        "Type": "System.String",
        "IsRequired": false
      },
      {
        "Name": "role",
        "Type": "System.String",
        "IsRequired": false
      }
    ],
    "ReturnTypes": [
      {
        "Type": "System.Void",
        "MediaTypes": [],
        "StatusCode": 200
      }
    ],
    "EndpointName": "PostUser"
  },
  {
    "ContainingType": "projeto.Controllers.UserController",
    "Method": "Get",
    "RelativePath": "User",
    "HttpMethod": "GET",
    "IsController": true,
    "Order": 0,
    "Parameters": [],
    "ReturnTypes": [
      {
        "Type": "System.Collections.Generic.IEnumerable\u00601[[projeto.Data.Models.User, AMoVeR-Logistica, Version=1.0.0.0, Culture=neutral, PublicKeyToken=null]]",
        "MediaTypes": [
          "text/plain",
          "application/json",
          "text/json"
        ],
        "StatusCode": 200
      }
    ],
    "EndpointName": "GetUsers"
  },
  {
    "ContainingType": "projeto.Controllers.UserController",
    "Method": "Put",
    "RelativePath": "User",
    "HttpMethod": "PUT",
    "IsController": true,
    "Order": 0,
    "Parameters": [
      {
        "Name": "ID",
        "Type": "System.Int32",
        "IsRequired": false
      },
      {
        "Name": "name",
        "Type": "System.String",
        "IsRequired": false
      },
      {
        "Name": "email",
        "Type": "System.String",
        "IsRequired": false
      },
      {
        "Name": "password",
        "Type": "System.String",
        "IsRequired": false
      },
      {
        "Name": "role",
        "Type": "System.String",
        "IsRequired": false
      }
    ],
    "ReturnTypes": [
      {
        "Type": "System.Void",
        "MediaTypes": [],
        "StatusCode": 200
      }
    ],
    "EndpointName": "UpdateUser"
  },
  {
    "ContainingType": "projeto.Controllers.UserController",
    "Method": "Delete",
    "RelativePath": "User",
    "HttpMethod": "DELETE",
    "IsController": true,
    "Order": 0,
    "Parameters": [
      {
        "Name": "ID",
        "Type": "System.Int32",
        "IsRequired": false
      }
    ],
    "ReturnTypes": [
      {
        "Type": "System.Void",
        "MediaTypes": [],
        "StatusCode": 200
      }
    ],
    "EndpointName": "DeleteUser"
  }
]